fibanez_social-0.0.1.dev1.dist-info/RECORD
fibanez_social-0.0.1.dev1.dist-info/DESCRIPTION.rst
fibanez_social-0.0.1.dev1.dist-info/metadata.json
fibanez_social-0.0.1.dev1.dist-info/top_level.txt
fibanez_social-0.0.1.dev1.dist-info/METADATA
fibanez_social-0.0.1.dev1.dist-info/WHEEL
fibanez_social/admin.py
fibanez_social/tests.py
fibanez_social/urls.py
fibanez_social/__init__.py
fibanez_social/settings.py
fibanez_social/wsgi.py
fibanez_social/migrations_django/__init__.py
fibanez_social/migrations_django/0001_initial.py
fibanez_social/models/facebook.py
fibanez_social/models/__init__.py
fibanez_social/models/linkedin.py
fibanez_social/models/twitter.py
fibanez_social/tests/test_linkdin.py
fibanez_social/tests/test_facebook.py
fibanez_social/tests/__init__.py
fibanez_social/tests/test_twitter.py
fibanez_social/templatetags/__init__.py
fibanez_social/templatetags/fibanez_social_tags.py
