Metadata-Version: 2.0
Name: fibanez-social
Version: 0.0.1.dev1
Summary: social network to add facebook, twitter and linkedin links
Home-page: https://github.com/fibanez6/fibanez_social
Author: Fernando Ibanez
Author-email: fibanez@fibanez.com
License: MIT
Keywords: social link
Platform: UNKNOWN
Classifier: Development Status :: 3 - Alpha
Classifier: Intended Audience :: Developers
Classifier: Topic :: Software Development :: Build Tools
Classifier: License :: OSI Approved :: MIT License
Classifier: Programming Language :: Python :: 2
Classifier: Programming Language :: Python :: 2.6
Classifier: Programming Language :: Python :: 2.7
Classifier: Programming Language :: Python :: 3
Classifier: Programming Language :: Python :: 3.2
Classifier: Programming Language :: Python :: 3.3
Classifier: Programming Language :: Python :: 3.4
Requires-Dist: Django (>=1.7)
